distance_correlation
