Metadata-Version: 2.1
Name: distance-correlation
Version: 0.0.2
Summary: Computes distance covariances/correlations between vectors and distance covariance/correlation matrices for data matrices
Home-page: https://github.com/asemic-horizon/distance_correlation
Author: Diego Navarro
Author-email: the.electric.me@gmail.com
License: UNKNOWN
Platform: UNKNOWN
Requires-Python: >=3.9
License-File: LICENSE
